setup.py
expressmoney_service/__init__.py
expressmoney_service/utils.py
expressmoney_service.egg-info/PKG-INFO
expressmoney_service.egg-info/SOURCES.txt
expressmoney_service.egg-info/dependency_links.txt
expressmoney_service.egg-info/requires.txt
expressmoney_service.egg-info/top_level.txt
expressmoney_service/api/__init__.py
expressmoney_service/api/client.py
expressmoney_service/api/contract.py
expressmoney_service/api/filter.py
expressmoney_service/api/id.py
expressmoney_service/api/point.py
expressmoney_service/points/__init__.py
expressmoney_service/points/absolute_insurance.py
expressmoney_service/points/contracts.py
expressmoney_service/points/da_data.py
expressmoney_service/points/efin.py
expressmoney_service/points/id_idx.py
expressmoney_service/points/idx_esia.py
expressmoney_service/points/megafon.py
expressmoney_service/points/nbki.py
expressmoney_service/points/ru_verificator.py
expressmoney_service/points/scoring_beeline.py
expressmoney_service/points/scoring_megafon.py
expressmoney_service/points/scoring_mts.py
expressmoney_service/points/scoring_nbki.py
expressmoney_service/points/server1c.py
expressmoney_service/points/smart_id_reader.py
expressmoney_service/points/sms_mts.py
expressmoney_service/points/tele2.py
expressmoney_service/points/tinkoff_id.py