Metadata-Version: 2.1
Name: expressmoney-service
Version: 1.4.17
Summary: Remote services
Home-page: UNKNOWN
Author: Development team
Author-email: dev@expressmoney.com
License: UNKNOWN
Platform: UNKNOWN
Requires-Python: >=3.7
